{
  "kind": "collectionType",
  "collectionName": "case_categories",
  "info": {
    "singularName": "case-category",
    "pluralName": "case-categories",
    "displayName": "Catégories Cas clients"
  },
  "options": {
    "draftAndPublish": false
  },
  "pluginOptions": {
    "i18n": {
      "localized": true
    }
  },
  "attributes": {
    "label": {
      "type": "string",
      "pluginOptions": {
        "i18n": {
          "localized": true
        }
      },
      "required": true
    }
  }
}
